LICENSE
MANIFEST.in
README.md
setup.cfg
setup.py
versioneer.py
scripts/sss
solutionspacescanner/.DS_Store
solutionspacescanner/__init__.py
solutionspacescanner/_version.py
solutionspacescanner/configs.py
solutionspacescanner/fos_calcs.py
solutionspacescanner/io_functions.py
solutionspacescanner/offset_calculator.py
solutionspacescanner/solutionspacescanner.py
solutionspacescanner/sssexception.py
solutionspacescanner.egg-info/PKG-INFO
solutionspacescanner.egg-info/SOURCES.txt
solutionspacescanner.egg-info/dependency_links.txt
solutionspacescanner.egg-info/requires.txt
solutionspacescanner.egg-info/top_level.txt
solutionspacescanner/data/1MUREA.mtfe
solutionspacescanner/data/README.md
solutionspacescanner/data/abs3.2_opls.prm
solutionspacescanner/data/look_and_say.dat
solutionspacescanner/data/test_data/1MUREA_HID.mtfe
solutionspacescanner/data/test_data/1MUREA_HIE.mtfe
solutionspacescanner/data/test_data/1MUREA_HIP.mtfe
solutionspacescanner/data/test_data/abs3.2_opls.prm
solutionspacescanner/data/test_data/bad_mtfe.mtfe
solutionspacescanner/data/test_data/bad_mtfe1.mtfe
solutionspacescanner/data/test_data/bad_mtfe2.mtfe
solutionspacescanner/data/test_data/bad_mtfe3.mtfe
solutionspacescanner/data/test_data/bad_mtfe4.mtfe
solutionspacescanner/data/test_data/good_mtfe.mtfe
solutionspacescanner/data/test_data/good_mtfe_scalar_1.mtfe
solutionspacescanner/data/test_data/good_mtfe_scalar_1.mtfe~
solutionspacescanner/pimms/__init__.py
solutionspacescanner/pimms/parser.py
solutionspacescanner/pimms/parser.py~
solutionspacescanner/tests/__init__.py
solutionspacescanner/tests/conftest.py
solutionspacescanner/tests/test_fos_calcs.py
solutionspacescanner/tests/test_his_complexity.py
solutionspacescanner/tests/test_io_functions.py
solutionspacescanner/tests/test_solutionspacescanner.py