Metadata-Version: 2.1
Name: solutionspacescanner
Version: 0.1.4
Summary: UNKNOWN
Home-page: UNKNOWN
Author: Alex Holehouse & Shahar Sukenik
Author-email: alex.holehouse@wustl.edu
License: LGPLv3
Platform: UNKNOWN
